<?xml version='1.0' encoding='utf-8' ?>
<!DOCTYPE LIGO_LW SYSTEM "http://ldas-sw.ligo.caltech.edu/doc/ligolwAPI/html/ligolw_dtd.txt"><LIGO_LW>
   <Table Name="process:table">
      <Column Name="program" Type="lstring"/>
      <Column Name="version" Type="lstring"/>
      <Column Name="cvs_repository" Type="lstring"/>
      <Column Name="cvs_entry_time" Type="int_4s"/>
      <Column Name="comment" Type="lstring"/>
      <Column Name="is_online" Type="int_4s"/>
      <Column Name="node" Type="lstring"/>
      <Column Name="username" Type="lstring"/>
      <Column Name="unix_procid" Type="int_4s"/>
      <Column Name="start_time" Type="int_4s"/>
      <Column Name="end_time" Type="int_4s"/>
      <Column Name="jobid" Type="int_4s"/>
      <Column Name="domain" Type="lstring"/>
      <Column Name="ifos" Type="lstring"/>
      <Column Name="process_id" Type="ilwd:char"/>
      <Stream Name="process:table" Type="Local" Delimiter=",">
         "inspinj","8cbd1b7187ce3ed9a825d6ed11cc432f3cfde9a5","CLEAN: All modifications committed",1196522994," ",0,"ldas-pcdev5","45454",1221272,1271690402,1271690402,0,"lalapps","","process:process_id:0"
      </Stream>
   </Table>
   <Table Name="process_params:table">
      <Column Name="program" Type="lstring"/>
      <Column Name="process:process_id" Type="ilwd:char"/>
      <Column Name="param" Type="lstring"/>
      <Column Name="type" Type="lstring"/>
      <Column Name="value" Type="lstring"/>
      <Stream Name="process_params:table" Type="Local" Delimiter=",">
         "inspinj","process:process_id:0","--gps-start-time","int","1126368017",
         "inspinj","process:process_id:0","--gps-end-time","int","1130371217",
         "inspinj","process:process_id:0","--f-lower","float","30.000000",
         "inspinj","process:process_id:0","--min-mtotal","float","1.000000e+01",
         "inspinj","process:process_id:0","--max-mtotal","float","1.000000e+02",
         "inspinj","process:process_id:0","--min-spin1","float","0.000000e+00",
         "inspinj","process:process_id:0","--max-spin1","float","9.980000e-01",
         "inspinj","process:process_id:0","--min-spin2","float","0.000000e+00",
         "inspinj","process:process_id:0","--max-spin2","float","9.980000e-01",
         "inspinj","process:process_id:0","--min-mratio","float","1.000000e+00",
         "inspinj","process:process_id:0","--max-mratio","float","1.000000e+01",
         "inspinj","process:process_id:0","--i-distr","string","fixed",
         "inspinj","process:process_id:0","--fixed-inc","float","0.000000e+00",
         "inspinj","process:process_id:0","--m-distr","string","totalMassRatio",
         "inspinj","process:process_id:0","--min-distance","float","1.000000e+03",
         "inspinj","process:process_id:0","--max-distance","float","1.000000e+03",
         "inspinj","process:process_id:0","--l-distr","string","random",
         "inspinj","process:process_id:0","--waveform","string","IMRPhenomDpseudoFourPN",
         "inspinj","process:process_id:0","--aligned","string","",
         "inspinj","process:process_id:0","--enable-spin","string","",
         "inspinj","process:process_id:0","--d-distr","string","uniform",
         "inspinj","process:process_id:0","--time-step","float","6.048000e+05",
         "inspinj","process:process_id:0","--seed","int","3"
      </Stream>
   </Table>
   <Table Name="sim_inspiral:table">
      <Column Name="process:process_id" Type="ilwd:char"/>
      <Column Name="waveform" Type="lstring"/>
      <Column Name="geocent_end_time" Type="int_4s"/>
      <Column Name="geocent_end_time_ns" Type="int_4s"/>
      <Column Name="h_end_time" Type="int_4s"/>
      <Column Name="h_end_time_ns" Type="int_4s"/>
      <Column Name="l_end_time" Type="int_4s"/>
      <Column Name="l_end_time_ns" Type="int_4s"/>
      <Column Name="g_end_time" Type="int_4s"/>
      <Column Name="g_end_time_ns" Type="int_4s"/>
      <Column Name="t_end_time" Type="int_4s"/>
      <Column Name="t_end_time_ns" Type="int_4s"/>
      <Column Name="v_end_time" Type="int_4s"/>
      <Column Name="v_end_time_ns" Type="int_4s"/>
      <Column Name="end_time_gmst" Type="real_8"/>
      <Column Name="source" Type="lstring"/>
      <Column Name="mass1" Type="real_4"/>
      <Column Name="mass2" Type="real_4"/>
      <Column Name="mchirp" Type="real_4"/>
      <Column Name="eta" Type="real_4"/>
      <Column Name="distance" Type="real_4"/>
      <Column Name="longitude" Type="real_4"/>
      <Column Name="latitude" Type="real_4"/>
      <Column Name="inclination" Type="real_4"/>
      <Column Name="coa_phase" Type="real_4"/>
      <Column Name="polarization" Type="real_4"/>
      <Column Name="psi0" Type="real_4"/>
      <Column Name="psi3" Type="real_4"/>
      <Column Name="alpha" Type="real_4"/>
      <Column Name="alpha1" Type="real_4"/>
      <Column Name="alpha2" Type="real_4"/>
      <Column Name="alpha3" Type="real_4"/>
      <Column Name="alpha4" Type="real_4"/>
      <Column Name="alpha5" Type="real_4"/>
      <Column Name="alpha6" Type="real_4"/>
      <Column Name="beta" Type="real_4"/>
      <Column Name="spin1x" Type="real_4"/>
      <Column Name="spin1y" Type="real_4"/>
      <Column Name="spin1z" Type="real_4"/>
      <Column Name="spin2x" Type="real_4"/>
      <Column Name="spin2y" Type="real_4"/>
      <Column Name="spin2z" Type="real_4"/>
      <Column Name="theta0" Type="real_4"/>
      <Column Name="phi0" Type="real_4"/>
      <Column Name="f_lower" Type="real_4"/>
      <Column Name="f_final" Type="real_4"/>
      <Column Name="eff_dist_h" Type="real_4"/>
      <Column Name="eff_dist_l" Type="real_4"/>
      <Column Name="eff_dist_g" Type="real_4"/>
      <Column Name="eff_dist_t" Type="real_4"/>
      <Column Name="eff_dist_v" Type="real_4"/>
      <Column Name="numrel_mode_min" Type="int_4s"/>
      <Column Name="numrel_mode_max" Type="int_4s"/>
      <Column Name="numrel_data" Type="lstring"/>
      <Column Name="amp_order" Type="int_4s"/>
      <Column Name="taper" Type="lstring"/>
      <Column Name="bandpass" Type="int_4s"/>
      <Column Name="simulation_id" Type="ilwd:char"/>
      <Stream Name="sim_inspiral:table" Type="Local" Delimiter=",">
         "process:process_id:0","IMRPhenomDpseudoFourPN",1126368017,0,1126368017,10987496,1126368017,2849695,1126368017,11784701,1126368017,18890562,1126368017,9432854,3.6144971161839348e+04,"",1.566397e+01,2.177591e+00,4.671328e+00,1.071550e-01,1.000000e+00,3.197740e+00,-1.080803e+00,0.000000e+00,1.864446e+00,3.248290e-01,0.000000e+00,0.000000e+00,0.000000e+00,0.000000e+00,0.000000e+00,0.000000e+00,0.000000e+00,0.000000e+00,0.000000e+00,0.000000e+00,0.000000e+00,0.000000e+00,7.587210e-01,0.000000e+00,0.000000e+00,-8.964829e-01,0.000000e+00,0.000000e+00,3.000000e+01,0.000000e+00,1.582413e+00,1.963564e+00,1.770665e+00,1.116681e+00,1.697111e+00,0,0,"",-1,"TAPER_NONE",0,"sim_inspiral:simulation_id:0",
         "process:process_id:0","IMRPhenomDpseudoFourPN",1126972817,0,1126972816,992031310,1126972816,987123911,1126972817,11022879,1126972817,11235869,1126972817,11372095,3.6189073878532654e+04,"",2.633919e+01,1.957688e+01,1.972489e+01,2.445775e-01,1.000000e+00,2.373803e+00,-3.572378e-01,0.000000e+00,5.449425e+00,1.580670e+00,0.000000e+00,0.000000e+00,0.000000e+00,0.000000e+00,0.000000e+00,0.000000e+00,0.000000e+00,0.000000e+00,0.000000e+00,0.000000e+00,0.000000e+00,0.000000e+00,3.815812e-01,0.000000e+00,0.000000e+00,-2.978436e-01,0.000000e+00,0.000000e+00,3.000000e+01,0.000000e+00,2.056057e+00,1.628029e+00,1.828175e+00,1.566396e+00,1.640562e+00,0,0,"",-1,"TAPER_NONE",0,"sim_inspiral:simulation_id:1",
         "process:process_id:0","IMRPhenomDpseudoFourPN",1127577617,0,1127577616,979057008,1127577616,981704269,1127577616,990471379,1127577616,992360715,1127577616,993095636,3.6233176595225952e+04,"",4.225407e+01,1.339335e+01,2.007085e+01,1.827544e-01,1.000000e+00,2.314348e+00,9.688176e-01,0.000000e+00,5.079341e+00,4.562544e+00,0.000000e+00,0.000000e+00,0.000000e+00,0.000000e+00,0.000000e+00,0.000000e+00,0.000000e+00,0.000000e+00,0.000000e+00,0.000000e+00,0.000000e+00,0.000000e+00,6.332378e-01,0.000000e+00,0.000000e+00,8.283662e-01,0.000000e+00,0.000000e+00,3.000000e+01,0.000000e+00,1.013479e+00,1.149206e+00,1.690756e+00,2.588505e+00,3.010738e+00,0,0,"",-1,"TAPER_NONE",0,"sim_inspiral:simulation_id:2",
         "process:process_id:0","IMRPhenomDpseudoFourPN",1128182417,0,1128182417,5965336,1128182416,996050129,1128182417,2916006,1128182417,21239595,1128182417,632472,3.6277279311919257e+04,"",3.027171e+01,3.597612e+00,8.246495e+00,9.493762e-02,1.000000e+00,3.709137e+00,-6.028611e-01,0.000000e+00,2.569434e-01,2.902769e+00,0.000000e+00,0.000000e+00,0.000000e+00,0.000000e+00,0.000000e+00,0.000000e+00,0.000000e+00,0.000000e+00,0.000000e+00,0.000000e+00,0.000000e+00,0.000000e+00,4.008150e-01,0.000000e+00,0.000000e+00,-6.886102e-01,0.000000e+00,0.000000e+00,3.000000e+01,0.000000e+00,2.243606e+00,2.479856e+00,2.916176e+00,1.000610e+00,2.746345e+00,0,0,"",-1,"TAPER_NONE",0,"sim_inspiral:simulation_id:3",
         "process:process_id:0","IMRPhenomDpseudoFourPN",1128787217,0,1128787216,998875355,1128787216,994257233,1128787217,16489495,1128787217,11630684,1128787217,16230765,3.6321382028612563e+04,"",4.642152e+01,1.660646e+01,2.356629e+01,1.940572e-01,1.000000e+00,2.571628e+00,-7.084912e-01,0.000000e+00,4.373811e+00,7.892643e-01,0.000000e+00,0.000000e+00,0.000000e+00,0.000000e+00,0.000000e+00,0.000000e+00,0.000000e+00,0.000000e+00,0.000000e+00,0.000000e+00,0.000000e+00,0.000000e+00,8.712450e-01,0.000000e+00,0.000000e+00,-6.979125e-01,0.000000e+00,0.000000e+00,3.000000e+01,0.000000e+00,4.558625e+00,3.307918e+00,1.264712e+00,1.728482e+00,1.301842e+00,0,0,"",-1,"TAPER_NONE",0,"sim_inspiral:simulation_id:4",
         "process:process_id:0","IMRPhenomDpseudoFourPN",1129392017,0,1129392016,981957364,1129392016,984029440,1129392017,5230068,1129392016,995550384,1129392017,7772779,3.6365484745305868e+04,"",1.530373e+01,5.071189e+00,7.449464e+00,1.869456e-01,1.000000e+00,2.359668e+00,2.913100e-01,0.000000e+00,1.726342e+00,2.546233e+00,0.000000e+00,0.000000e+00,0.000000e+00,0.000000e+00,0.000000e+00,0.000000e+00,0.000000e+00,0.000000e+00,0.000000e+00,0.000000e+00,0.000000e+00,0.000000e+00,-7.110490e-01,0.000000e+00,0.000000e+00,-7.869171e-01,0.000000e+00,0.000000e+00,3.000000e+01,0.000000e+00,1.174378e+00,1.282548e+00,2.037353e+00,2.063155e+00,2.493192e+00,0,0,"",-1,"TAPER_NONE",0,"sim_inspiral:simulation_id:5",
         "process:process_id:0","IMRPhenomDpseudoFourPN",1129996817,0,1129996816,982207452,1129996816,987519814,1129996817,3744330,1129996816,988640037,1129996817,6768277,3.6409587461999166e+04,"",1.170203e+01,1.545864e+00,3.388677e+00,1.030716e-01,1.000000e+00,2.145173e+00,4.592088e-01,0.000000e+00,6.113730e+00,2.348138e+00,0.000000e+00,0.000000e+00,0.000000e+00,0.000000e+00,0.000000e+00,0.000000e+00,0.000000e+00,0.000000e+00,0.000000e+00,0.000000e+00,0.000000e+00,0.000000e+00,-5.247532e-01,0.000000e+00,0.000000e+00,-1.593447e-01,0.000000e+00,0.000000e+00,3.000000e+01,0.000000e+00,1.178300e+00,1.637385e+00,2.015972e+00,1.589690e+00,2.858003e+00,0,0,"",-1,"TAPER_NONE",0,"sim_inspiral:simulation_id:6"
      </Stream>
   </Table>
</LIGO_LW>